odoo10_addon_html_text-10.0.1.0.1-py3.8-nspkg.pth
odoo/addons/html_text/README.rst
odoo/addons/html_text/__init__.py
odoo/addons/html_text/__manifest__.py
odoo/addons/html_text/i18n/ca.po
odoo/addons/html_text/i18n/de.po
odoo/addons/html_text/i18n/es.po
odoo/addons/html_text/i18n/es_ES.po
odoo/addons/html_text/i18n/hr.po
odoo/addons/html_text/i18n/html_text.pot
odoo/addons/html_text/i18n/it.po
odoo/addons/html_text/i18n/tr.po
odoo/addons/html_text/models/__init__.py
odoo/addons/html_text/models/ir_fields_converter.py
odoo/addons/html_text/static/description/icon.png
odoo/addons/html_text/tests/__init__.py
odoo/addons/html_text/tests/test_extractor.py
odoo10_addon_html_text-10.0.1.0.1.dist-info/METADATA
odoo10_addon_html_text-10.0.1.0.1.dist-info/WHEEL
odoo10_addon_html_text-10.0.1.0.1.dist-info/namespace_packages.txt
odoo10_addon_html_text-10.0.1.0.1.dist-info/top_level.txt
odoo10_addon_html_text-10.0.1.0.1.dist-info/RECORD
