Metadata-Version: 2.1
Name: odoo10-addon-html-text
Version: 10.0.1.0.1
Summary: Generate excerpts from any HTML field
Home-page: https://tecnativa.com
Author: Grupo ESOC Ingeniería de Servicios, Tecnativa, Odoo Community Association (OCA)
Author-email: support@odoo-community.org
License: AGPL-3
Platform: UNKNOWN
Classifier: Programming Language :: Python
Classifier: Framework :: Odoo
Classifier: Framework :: Odoo :: 10.0
Classifier: License :: OSI Approved :: GNU Affero General Public License v3
Requires-Python: ~=2.7
Requires-Dist: lxml
Requires-Dist: odoo (<10.1dev,>=10.0)
